{"image_name":"1690793589893040216.png","media":{"taken_at":1515778324,"id":"1690793589893040216_4374104135","pk":"1690793589893040216","saved_collection_ids":["17903971393169662"],"media_type":1,"original_width":706,"original_height":567,"image_versions2":{"candidates":["https://scontent-cdg2-1.cdninstagram.com/v/t51.2885-15/e35/37700435_285524302215269_8719782061927301120_n.jpg?_nc_ht=scontent-cdg2-1.cdninstagram.com&oh=9a8bb677b1057da410d1f2057f0e9aa1&oe=5DD7478C&ig_cache_key=MTY5MDc5MzU4OTg5MzA0MDIxNg%3D%3D.2","https://scontent-cdg2-1.cdninstagram.com/v/t51.2885-15/e35/s480x480/37700435_285524302215269_8719782061927301120_n.jpg?_nc_ht=scontent-cdg2-1.cdninstagram.com&oh=291669a55dbbba0fa4817c68797d3eb4&oe=5DD77E64&ig_cache_key=MTY5MDc5MzU4OTg5MzA0MDIxNg%3D%3D.2"]},"user":{"pk":4374104135,"username":"le__dauphin","is_private":true,"profile_pic_url":"https://scontent-cdg2-1.cdninstagram.com/vp/c73aa5ecb1ab020ff95003d3e5ac97cf/5DD6C941/t51.2885-19/s150x150/37240578_1055788007919632_3808962282981949440_n.jpg?_nc_ht=scontent-cdg2-1.cdninstagram.com","profile_pic_id":"1465456507888925395_4374104135"},"comment_count":2,"like_count":695,"has_liked":false,"caption":{"pk":"17904609649119383","user_id":4374104135,"media_id":"1690793589893040216","text":"Plans for the weekend ⛓ via @sheetnoise","created_at":1515778325}}}