{"image_name":"1714060637958934404.png","media":{"taken_at":1518551972,"id":"1714060637958934404_1630485968","pk":"1714060637958934404","saved_collection_ids":[],"media_type":1,"original_width":1080,"original_height":1080,"image_versions2":{"candidates":["https://scontent-cdg2-1.cdninstagram.com/v/t51.2885-15/e35/27891584_186114865321635_168596209605279744_n.jpg?_nc_ht=scontent-cdg2-1.cdninstagram.com&se=7&oh=e4040e5e5a507cfd6a5ef3142046e3f9&oe=5DD49DE9&ig_cache_key=MTcxNDA2MDYzNzk1ODkzNDQwNA%3D%3D.2","https://scontent-cdg2-1.cdninstagram.com/v/t51.2885-15/e35/s480x480/27891584_186114865321635_168596209605279744_n.jpg?_nc_ht=scontent-cdg2-1.cdninstagram.com&oh=1872a0e000805724eab10105d7d78dce&oe=5DD1322A&ig_cache_key=MTcxNDA2MDYzNzk1ODkzNDQwNA%3D%3D.2"]},"user":{"pk":1630485968,"username":"mangez_mua","is_private":false,"profile_pic_url":"https://scontent-cdg2-1.cdninstagram.com/vp/c097017156817f68e3044ee12030dc0e/5DD02B79/t51.2885-19/s150x150/13269577_506495896211426_794710845_a.jpg?_nc_ht=scontent-cdg2-1.cdninstagram.com","profile_pic_id":"1265190383790269630_1630485968"},"next_max_id":"17851678825238809","comment_count":15,"like_count":91,"has_liked":false,"caption":{"pk":"17864743462208927","user_id":1630485968,"media_id":"1714060637958934404","text":"Encore des champignons?\nOui mais à la base ils étaient tous prévus pour cette soupe.\nSauf qu’il y a eu de l’impro hier soir...\nMais pas question de renoncer à mon petit plat bien roboratif et réconfortant après ma looongue journée de boulot où j’ai eu bien froid toute la journée...\n.\n🔸 Potage épais de champignons, céleri et sarrasin🔸\n.\n(Note à moi-même : préférer du kasha pour donner une petite note fumée).\n.\n~~~~~~~~~~~~~~~~~~~~~~~~~~~~\n.\nIdeal for warm up after looong day at work.\n.\n🔹Creamy soup of mushrooms, celery, and buckwheat🔹\n.\n*********************************\n#soupe #soup #potage #tropbonquandyfaitfroid #soupoftheday #soupedujour #winteriscoming #lhiverestla #buckwheat #sarrasin #creamy #mushroom #champignons #🥣 #🍄 #funghi #glaglagla #brrrr #comfortfood #winter #hiver #belowzero #souszero #❄️\n#mangezmua #lapetitecuillereenbois #littlewoodenspoon","created_at":1518587387}}}