{"image_name":"1776946335946901834.png","media":{"taken_at":1526048532,"id":"1776946335946901834_787132","pk":"1776946335946901834","saved_collection_ids":["17912993254193099"],"media_type":1,"original_width":1080,"original_height":1080,"image_versions2":{"candidates":["https://scontent-cdg2-1.cdninstagram.com/v/t51.2885-15/e35/31338712_197590147521859_6353745678765654016_n.jpg?_nc_ht=scontent-cdg2-1.cdninstagram.com&se=7&oh=dfc61f405aa3f677f8e528e3f401bb0c&oe=5DE8DF1F&ig_cache_key=MTc3Njk0NjMzNTk0NjkwMTgzNA%3D%3D.2","https://scontent-cdg2-1.cdninstagram.com/v/t51.2885-15/e35/s480x480/31338712_197590147521859_6353745678765654016_n.jpg?_nc_ht=scontent-cdg2-1.cdninstagram.com&oh=11beb70f4d4293fb35e8ae90889361d5&oe=5DCAD2F7&ig_cache_key=MTc3Njk0NjMzNTk0NjkwMTgzNA%3D%3D.2"]},"user":{"pk":787132,"username":"natgeo","is_private":false,"profile_pic_url":"https://scontent-cdg2-1.cdninstagram.com/vp/b9a707a04591a0a53d205fc3bdaeb3c7/5DE9B4E8/t51.2885-19/s150x150/13597791_261499887553333_1855531912_a.jpg?_nc_ht=scontent-cdg2-1.cdninstagram.com","profile_pic_id":"1288575635841480803_787132"},"next_max_id":"17889068344355887","comment_count":1561,"like_count":359940,"has_liked":false,"caption":{"pk":"17855483941252002","user_id":787132,"media_id":"1776946335946901834","text":"Photo by @stephenwilkes. Photographing the beautiful Ipanema Beach always makes me think of that great bossa nova jazz song, \"The Girl from Ipanema\". To see more photos from my travels near and far, visit me @stephenwilkes.\n\n#DayToNight #StephenWilkes #IpanemaBeach #Ipanema #Beach #RioDeJaneiro #Spiderman","created_at":1526048532}}}