{"image_name":"1831132482625186563.png","media":{"taken_at":1532508024,"id":"1831132482625186563_2089077785","pk":"1831132482625186563","saved_collection_ids":["17912993254193099"],"media_type":1,"original_width":1080,"original_height":1349,"image_versions2":{"candidates":["https://scontent-cdg2-1.cdninstagram.com/v/t51.2885-15/e35/37001123_213470406008535_8779222042776961024_n.jpg?_nc_ht=scontent-cdg2-1.cdninstagram.com&se=7&oh=23c23c633a38863c5f7bc0f3e7dc41e5&oe=5DDB7F6D&ig_cache_key=MTgzMTEzMjQ4MjYyNTE4NjU2Mw%3D%3D.2","https://scontent-cdg2-1.cdninstagram.com/v/t51.2885-15/e35/p480x480/37001123_213470406008535_8779222042776961024_n.jpg?_nc_ht=scontent-cdg2-1.cdninstagram.com&oh=6bb949c4a050091627e3fa4a57ffbeca&oe=5DD83C96&ig_cache_key=MTgzMTEzMjQ4MjYyNTE4NjU2Mw%3D%3D.2"]},"user":{"pk":2089077785,"username":"fotokino","is_private":false,"profile_pic_url":"https://scontent-cdg2-1.cdninstagram.com/vp/c420affbb3ba4fcf12dc04d07720246e/5DDE4433/t51.2885-19/s150x150/40998572_1915845415386202_8508666530790113280_n.jpg?_nc_ht=scontent-cdg2-1.cdninstagram.com","profile_pic_id":"1868272574046048883_2089077785"},"comment_count":0,"like_count":244,"has_liked":false,"caption":{"pk":"17864309689269511","user_id":2089077785,"media_id":"1831132482625186563","text":"Fotokino en vacances du mercredi au dimanche de 14h30 à 18h30 ! \n#cestlesvacances","created_at":1532508024}}}