{"image_name":"1937883454315624668.png","media":{"taken_at":1545233731,"id":"1937883454315624668_2300387841","pk":"1937883454315624668","saved_collection_ids":["17905848295164083"],"media_type":1,"original_width":1080,"original_height":1080,"image_versions2":{"candidates":["https://scontent-cdg2-1.cdninstagram.com/v/t51.2885-15/e35/46522505_376809639734136_8657587638634595164_n.jpg?_nc_ht=scontent-cdg2-1.cdninstagram.com&se=7&oh=defecf5f863ca5301b580a2506899c5c&oe=5DE20BC2&ig_cache_key=MTkzNzg4MzQ1NDMxNTYyNDY2OA%3D%3D.2","https://scontent-cdg2-1.cdninstagram.com/v/t51.2885-15/e35/s480x480/46522505_376809639734136_8657587638634595164_n.jpg?_nc_ht=scontent-cdg2-1.cdninstagram.com&oh=af471efd8a662dc69f973d0f142dbe58&oe=5DE2882A&ig_cache_key=MTkzNzg4MzQ1NDMxNTYyNDY2OA%3D%3D.2"]},"user":{"pk":2300387841,"username":"leah_gordon_1804","is_private":false,"profile_pic_url":"https://scontent-cdg2-1.cdninstagram.com/vp/207ac68c55ca1fc2b0287ddbbd3d74b1/5DCACD41/t51.2885-19/s150x150/12269708_1069825213051767_83302956_a.jpg?_nc_ht=scontent-cdg2-1.cdninstagram.com"},"comment_count":0,"like_count":38,"has_liked":false,"caption":{"pk":"17993002804125360","user_id":2300387841,"media_id":"1937883454315624668","text":"#gustavedore #paradiselost #milton lucifer speaks to death & sin","created_at":1545233825}}}