{"image_name":"1969960146713441434.png","media":{"taken_at":1549057571,"id":"1969960146713441434_1006372709","pk":"1969960146713441434","saved_collection_ids":["17910006628153093"],"media_type":1,"original_width":1080,"original_height":1245,"image_versions2":{"candidates":["https://scontent-cdg2-1.cdninstagram.com/v/t51.2885-15/e35/50583834_354015355198882_907063088025868159_n.jpg?_nc_ht=scontent-cdg2-1.cdninstagram.com&se=7&oh=b8dfc4c5a2e630a7600975d5548a5008&oe=5DDDCD49&ig_cache_key=MTk2OTk2MDE0NjcxMzQ0MTQzNA%3D%3D.2","https://scontent-cdg2-1.cdninstagram.com/v/t51.2885-15/e35/p480x480/50583834_354015355198882_907063088025868159_n.jpg?_nc_ht=scontent-cdg2-1.cdninstagram.com&oh=26088930ffdd74e43cc310b0bdecd5f1&oe=5DD1553F&ig_cache_key=MTk2OTk2MDE0NjcxMzQ0MTQzNA%3D%3D.2"]},"user":{"pk":1006372709,"username":"templodeafrodita","is_private":false,"profile_pic_url":"https://scontent-cdg2-1.cdninstagram.com/vp/469b9cfcec3c04af82d22c382f0cb037/5DCDBDA5/t51.2885-19/s150x150/57363202_411899779359551_4558989346685845504_n.jpg?_nc_ht=scontent-cdg2-1.cdninstagram.com","profile_pic_id":"2021218715974312461_1006372709"},"next_max_id":"17896704181342211","comment_count":16,"like_count":2811,"has_liked":false,"caption":{"pk":"18029135806030615","user_id":1006372709,"media_id":"1969960146713441434","text":"Nos vemos hoy . Noche de Perreo . 🔥 Dame Paleta 🍭","created_at":1549057572}}}