{"image_name":"2023442486798850122.png","media":{"taken_at":1555433163,"id":"2023442486798850122_46790485","pk":"2023442486798850122","saved_collection_ids":[],"media_type":1,"original_width":1080,"original_height":1080,"image_versions2":{"candidates":["https://scontent-cdg2-1.cdninstagram.com/v/t51.2885-15/e35/55917962_794479850935164_2172216973379680858_n.jpg?_nc_ht=scontent-cdg2-1.cdninstagram.com&se=7&oh=e9d72beb02f95b2803f6e6238ca244ee&oe=5DD8D9CA&ig_cache_key=MjAyMzQ0MjQ4Njc5ODg1MDEyMg%3D%3D.2","https://scontent-cdg2-1.cdninstagram.com/v/t51.2885-15/e35/s480x480/55917962_794479850935164_2172216973379680858_n.jpg?_nc_ht=scontent-cdg2-1.cdninstagram.com&oh=de31596f0e94eb3b67ce8856e7635ab3&oe=5DCCF322&ig_cache_key=MjAyMzQ0MjQ4Njc5ODg1MDEyMg%3D%3D.2"]},"user":{"pk":46790485,"username":"veroniqueparis","is_private":false,"profile_pic_url":"https://scontent-cdg2-1.cdninstagram.com/vp/31bdba5af7649c473f361d120ff7a028/5DD205CB/t51.2885-19/11008118_848945298496070_1697543684_a.jpg?_nc_ht=scontent-cdg2-1.cdninstagram.com"},"comment_count":2,"like_count":94,"has_liked":true,"caption":{"pk":"17989271194218257","user_id":46790485,"media_id":"2023442486798850122","text":"Notre-Dame de Paris\n@liberationfr directeur artistique @nicolasvaloteau photographe @gvdh_photo \n#notredame #notredrame #notredamedeparis #liberation #lejourdapres #fluctuatnecmergitur #paris","created_at":1555450192}}}