{"image_name":"2029365832810832538.png","media":{"taken_at":1556139280,"id":"2029365832810832538_215438190","pk":"2029365832810832538","saved_collection_ids":["17904833158171396"],"media_type":1,"original_width":500,"original_height":305,"image_versions2":{"candidates":["https://scontent-cdg2-1.cdninstagram.com/v/t51.2885-15/e35/57000896_186439852340351_4034372280096513676_n.jpg?_nc_ht=scontent-cdg2-1.cdninstagram.com&oh=5119b991b125cf0d3c247f12c3aaf613&oe=5DE4AB95&ig_cache_key=MjAyOTM2NTgzMjgxMDgzMjUzOA%3D%3D.2","https://scontent-cdg2-1.cdninstagram.com/v/t51.2885-15/e35/s480x480/57000896_186439852340351_4034372280096513676_n.jpg?_nc_ht=scontent-cdg2-1.cdninstagram.com&oh=5db7b18b1beb76a66beef59b66e17f4f&oe=5DEE117D&ig_cache_key=MjAyOTM2NTgzMjgxMDgzMjUzOA%3D%3D.2"]},"user":{"pk":215438190,"username":"vincentlacoste","is_private":false,"profile_pic_url":"https://scontent-cdg2-1.cdninstagram.com/vp/e8de35ec42dec216bee903f6fa5dd1a6/5DD59FD8/t51.2885-19/s150x150/25022281_811477089039901_4737185645716307968_n.jpg?_nc_ht=scontent-cdg2-1.cdninstagram.com","profile_pic_id":"1684435880120787490_215438190"},"next_max_id":"17846150677541856","comment_count":38,"like_count":3019,"has_liked":true,"caption":{"pk":"18030101887184154","user_id":215438190,"media_id":"2029365832810832538","text":"💔","created_at":1556139281}}}