{"image_name":"2030726144434076365.png","media":{"taken_at":1556301442,"id":"2030726144434076365_6181317688","pk":"2030726144434076365","saved_collection_ids":["18043194847098819"],"media_type":1,"original_width":548,"original_height":422,"image_versions2":{"candidates":["https://scontent-cdg2-1.cdninstagram.com/v/t51.2885-15/e35/57062198_379438769317955_8029973142290915868_n.jpg?_nc_ht=scontent-cdg2-1.cdninstagram.com&oh=423165baf51c89aef812b7db7b3929d5&oe=5DE51F06&ig_cache_key=MjAzMDcyNjE0NDQzNDA3NjM2NQ%3D%3D.2","https://scontent-cdg2-1.cdninstagram.com/v/t51.2885-15/e35/s480x480/57062198_379438769317955_8029973142290915868_n.jpg?_nc_ht=scontent-cdg2-1.cdninstagram.com&oh=92ab355de607bc335b4af92a1add068e&oe=5DE126EE&ig_cache_key=MjAzMDcyNjE0NDQzNDA3NjM2NQ%3D%3D.2"]},"user":{"pk":6181317688,"username":"thecollageempire","is_private":false,"profile_pic_url":"https://scontent-cdg2-1.cdninstagram.com/vp/5d0c52e3c20fda27b149e590d6741428/5DD83A33/t51.2885-19/s150x150/26371461_1843572425934495_1973108065976713216_n.jpg?_nc_ht=scontent-cdg2-1.cdninstagram.com","profile_pic_id":"1697213651617063707_6181317688"},"next_max_id":"17908547695332171","comment_count":109,"like_count":12171,"has_liked":false,"caption":{"pk":"17925523723292838","user_id":6181317688,"media_id":"2030726144434076365","text":"Yves Marc\n#yvesmarc\n#thecollageempire\n#theatre#costume#mask#creature#creative#bestiary#dance#ballo#collage#collageary#collageartist#mixedmediaart#mixedmediaartist#contempirarycollage#contemporaryart","created_at":1556301443}}}