{"image_name":"2053921390268092574.png","media":{"taken_at":1559066531,"id":"2053921390268092574_1642394224","pk":"2053921390268092574","saved_collection_ids":[],"media_type":1,"original_width":1440,"original_height":1440,"image_versions2":{"candidates":["https://scontent-cdg2-1.cdninstagram.com/v/t51.2885-15/e35/60830531_352863065367916_5417736385925052697_n.jpg?_nc_ht=scontent-cdg2-1.cdninstagram.com&se=7&oh=f086155a6f391b415b653a4515cfca44&oe=5DDD78CB&ig_cache_key=MjA1MzkyMTM5MDI2ODA5MjU3NA%3D%3D.2","https://scontent-cdg2-1.cdninstagram.com/v/t51.2885-15/e35/s480x480/60830531_352863065367916_5417736385925052697_n.jpg?_nc_ht=scontent-cdg2-1.cdninstagram.com&oh=09af98136103bdaf78c3f11338392d40&oe=5DD9B323&ig_cache_key=MjA1MzkyMTM5MDI2ODA5MjU3NA%3D%3D.2"]},"user":{"pk":1642394224,"username":"simon_costin","is_private":false,"profile_pic_url":"https://scontent-cdg2-1.cdninstagram.com/vp/86a35482322b257d2fda63ed8e0c19fb/5DD02E48/t51.2885-19/s150x150/19228218_564361277285851_1072819355219132416_a.jpg?_nc_ht=scontent-cdg2-1.cdninstagram.com","profile_pic_id":"1541338700603880138_1642394224"},"next_max_id":"18054135001111755","comment_count":8,"like_count":351,"has_liked":false,"caption":{"pk":"18043101790095623","user_id":1642394224,"media_id":"2053921390268092574","text":"Lucifer, my favourite fallen angel #gustavedore #paradiselost #milton #fallenangel #fallenangels","created_at":1559066533}}}