{"image_name":"2078571347139117989.png","media":{"taken_at":1562005035,"id":"2078571347139117989_1537672550","pk":"2078571347139117989","saved_collection_ids":[],"media_type":1,"original_width":1080,"original_height":1350,"image_versions2":{"candidates":["https://scontent-cdg2-1.cdninstagram.com/v/t51.2885-15/e35/65103282_458429874954066_5917815789399937118_n.jpg?_nc_ht=scontent-cdg2-1.cdninstagram.com&se=7&oh=714aeeef2837b6732b634289c516a55d&oe=5DD751C9&ig_cache_key=MjA3ODU3MTM0NzEzOTExNzk4OQ%3D%3D.2","https://scontent-cdg2-1.cdninstagram.com/v/t51.2885-15/e35/p480x480/65103282_458429874954066_5917815789399937118_n.jpg?_nc_ht=scontent-cdg2-1.cdninstagram.com&oh=2b34902f5dac531f30ea0c28e42513a1&oe=5DDFC132&ig_cache_key=MjA3ODU3MTM0NzEzOTExNzk4OQ%3D%3D.2"]},"user":{"pk":1537672550,"username":"ktizinzin","is_private":true,"profile_pic_url":"https://scontent-cdg2-1.cdninstagram.com/vp/a1643567958c19fd7b8401ecb3c3e5b9/5DEA1EFA/t51.2885-19/s150x150/13437402_249963038715965_313011593_a.jpg?_nc_ht=scontent-cdg2-1.cdninstagram.com","profile_pic_id":"1271729337047440872_1537672550"},"next_max_id":"17909556670316932","comment_count":3,"like_count":26,"has_liked":false,"caption":{"pk":"18012501121212562","user_id":1537672550,"media_id":"2078571347139117989","text":"Burger tomate, mozzarella et pesto 🍅","created_at":1562005038}}}