{"image_name":"2084971712505213023.png","media":{"taken_at":1562768048,"id":"2084971712505213023_981943565","pk":"2084971712505213023","saved_collection_ids":[],"media_type":2,"original_width":720,"original_height":720,"image_versions2":{"candidates":["https://scontent-cdg2-1.cdninstagram.com/v/t51.2885-15/e35/65512915_1042284275980654_9183881125083714423_n.jpg?_nc_ht=scontent-cdg2-1.cdninstagram.com&oh=21a72cde3f1bd64a54a63a9901ea3a79&oe=5D47C11C","https://scontent-cdg2-1.cdninstagram.com/v/t51.2885-15/e35/s480x480/65512915_1042284275980654_9183881125083714423_n.jpg?_nc_ht=scontent-cdg2-1.cdninstagram.com&oh=bf917b028b838ec8b46d4ef3b093194a&oe=5D4808DC"]},"user":{"pk":981943565,"username":"fondationcartier","is_private":false,"profile_pic_url":"https://scontent-cdg2-1.cdninstagram.com/vp/3df08a4831910000dd7986285df87a00/5DD633AE/t51.2885-19/s150x150/27878640_167702843872849_2675854123936514048_n.jpg?_nc_ht=scontent-cdg2-1.cdninstagram.com","profile_pic_id":"1718192549280968393_981943565"},"next_max_id":"17842657729553922","comment_count":114,"like_count":4063,"has_liked":true,"caption":{"pk":"18077226967069232","user_id":981943565,"media_id":"2084971712505213023","text":"Exposition « Nous les Arbres » 12/07 - 10/11 !\n#FondationCartier #NouslesArbres #Trees #exhibition #Nature #Plants","created_at":1562849962}}}