{"image_name":"2101403793917208005.png","media":{"taken_at":1564726875,"id":"2101403793917208005_6436004718","pk":"2101403793917208005","saved_collection_ids":["17871356509248070"],"media_type":1,"original_width":1080,"original_height":1080,"image_versions2":{"candidates":["https://scontent-cdg2-1.cdninstagram.com/v/t51.2885-15/e35/66213007_361536724529441_8743966289854456236_n.jpg?_nc_ht=scontent-cdg2-1.cdninstagram.com&se=7&oh=035d4254189317ffa67922e0ecb614f6&oe=5DCAF3F8&ig_cache_key=MjEwMTQwMzc5MzkxNzIwODAwNQ%3D%3D.2","https://scontent-cdg2-1.cdninstagram.com/v/t51.2885-15/e35/s480x480/66213007_361536724529441_8743966289854456236_n.jpg?_nc_ht=scontent-cdg2-1.cdninstagram.com&oh=987d1e4059051e5965f104261d72304d&oe=5DE72E10&ig_cache_key=MjEwMTQwMzc5MzkxNzIwODAwNQ%3D%3D.2"]},"user":{"pk":6436004718,"username":"cinemamonamourpage","is_private":false,"profile_pic_url":"https://scontent-cdg2-1.cdninstagram.com/vp/537efbe55a8e3bbfad3e910f2a568412/5DE816FF/t51.2885-19/s150x150/27578348_533817883659868_3182834893939802112_n.jpg?_nc_ht=scontent-cdg2-1.cdninstagram.com","profile_pic_id":"1714597560671564599_6436004718"},"next_max_id":"18058236526191877","comment_count":21,"like_count":3194,"has_liked":false,"caption":{"pk":"18020536054208454","user_id":6436004718,"media_id":"2101403793917208005","text":"Brief Crossing (2001) dir. Catherine Breillat\n\n#briefcrossing #cinema #movielovers #movieoftheday #filmoftheday #movies #cinephilecommunity #cinephile #cinephiles #cinéphiles #cinemamonamour #cinema #movielovers #movieoftheday #filmoftheday #movies #cinephilecommunity #cinephile #cinephiles #cinéphiles #cinemamonamour #cinema #movielovers","created_at":1564726875}}}