{"media":{"taken_at":1565035860,"id":"2103995755878848202_6436004718","pk":"2103995755878848202","saved_collection_ids":["17871356509248070"],"media_type":1,"original_width":1080,"original_height":1080,"user":{"pk":6436004718,"username":"cinemamonamourpage","is_private":false,"profile_pic_url":"https://scontent-cdg2-1.cdninstagram.com/vp/537efbe55a8e3bbfad3e910f2a568412/5DE816FF/t51.2885-19/s150x150/27578348_533817883659868_3182834893939802112_n.jpg?_nc_ht=scontent-cdg2-1.cdninstagram.com","profile_pic_id":"1714597560671564599_6436004718"},"next_max_id":"18073868023098406","comment_count":37,"like_count":6122,"has_liked":false,"caption":{"pk":"17863773691457841","user_id":6436004718,"media_id":"2103995755878848202","text":"Immoral Tales (1974) dir. Walerian Borowczyk\n\n#immoraltales #walerianborowczyk #cinema #movielovers #movieoftheday #filmoftheday #movies #cinephilecommunity #cinephile #cinephiles #cinéphiles #cinemamonamour #cinema #movielovers #movieoftheday #filmoftheday #movies #cinephilecommunity #cinephile #cinephiles","created_at":1565035861}}}